django_range_merge/__init__.py
django_range_merge/apps.py
django_range_merge/models.py
django_range_merge/urls.py
django_range_merge/migrations/0001_initial.py
django_range_merge/migrations/__init__.py
django_range_merge-2024.10.1.dist-info/LICENSE
django_range_merge-2024.10.1.dist-info/METADATA
django_range_merge-2024.10.1.dist-info/WHEEL
django_range_merge-2024.10.1.dist-info/top_level.txt
django_range_merge-2024.10.1.dist-info/RECORD
