Metadata-Version: 2.1
Name: django-range-merge
Version: 2024.10.1
Summary: Enables the range_merge Aggregate for Django on Postgres. range_merge 'Computes the smallest range that includes ... the given ranges'.
Author-email: Jack Linke <jacklinke@gmail.com>
License: MIT
Project-URL: Homepage, https://github.com/OmenApps/django-range-merge
Project-URL: Repository, https://github.com/OmenApps/django-range-merge
Project-URL: Changelog, https://github.com/OmenApps/django-range-merge/releases
Classifier: Environment :: Web Environment
Classifier: Framework :: Django
Classifier: Framework :: Django :: 4.2
Classifier: Framework :: Django :: 5.0
Classifier: Framework :: Django :: 5.1
Classifier: Development Status :: 4 - Beta
Classifier: Intended Audience :: Developers
Classifier: License :: OSI Approved :: MIT License
Classifier: Operating System :: OS Independent
Classifier: Programming Language :: Python
Classifier: Programming Language :: Python :: 3
Classifier: Programming Language :: Python :: 3.10
Classifier: Programming Language :: Python :: 3.11
Classifier: Programming Language :: Python :: 3.12
Classifier: Programming Language :: Python :: 3.13
Classifier: Topic :: Database
Requires-Python: <4.0,>=3.10
License-File: LICENSE
Requires-Dist: django >=4.2.15
